modelnotes/__init__.py
modelnotes/admin.py
modelnotes/apps.py
modelnotes/fields.py
modelnotes/models.py
modelnotes/urls.py
modelnotes/migrations/0001_initial.py
modelnotes/migrations/__init__.py
modelnotes/templates/modelnotes/ajax/detail_note.htm
modelnotes/templates/modelnotes/form/create_note.htm
modelnotes/templates/modelnotes/form/update_note.htm
modelnotes/templates/modelnotes/snippet/select_options.htm
modelnotes/templates/modelnotes/table/list_notes.htm
modelnotes/templates/modelnotes/table/list_notes_minimal.htm
modelnotes/templatetags/__init__.py
modelnotes/templatetags/modelnotes_tags.py
modelnotes/views/__init__.py
modelnotes/views/action.py
modelnotes/views/ajax.py
modelnotes/views/api.py
modelnotes/views/gui.py
modelnotes/views/htmx.py
django_modelnotes-0.0.0.dev1.dist-info/LICENSE
django_modelnotes-0.0.0.dev1.dist-info/METADATA
django_modelnotes-0.0.0.dev1.dist-info/WHEEL
django_modelnotes-0.0.0.dev1.dist-info/top_level.txt
django_modelnotes-0.0.0.dev1.dist-info/zip-safe
django_modelnotes-0.0.0.dev1.dist-info/RECORD
