Metadata-Version: 2.1
Name: django-modelnotes
Version: 0.0.0.dev1
Home-page: https://github.com/davidslusser/django-modelnotes
Author: David Slusser
Author-email: dbslusser@gmail.com
License: GNU
Platform: any
License-File: LICENSE
Requires-Dist: django-auditlog
Requires-Dist: django-braces
Requires-Dist: django-handyhelpers (==0.2.*)
Provides-Extra: dev
Requires-Dist: bandit (~=1.7) ; extra == 'dev'
Requires-Dist: black (~=22.3) ; extra == 'dev'
Requires-Dist: build (~=0.8) ; extra == 'dev'
Requires-Dist: flake9 ; extra == 'dev'
Requires-Dist: mypy ; extra == 'dev'
Requires-Dist: pylint (~=2.14) ; extra == 'dev'
Requires-Dist: pytest (~=7.1) ; extra == 'dev'
Requires-Dist: pytest-cov (~=3.0) ; extra == 'dev'
